iza/__init__.py
iza/_modidx.py
iza/commands.py
iza/imp.py
iza/nbs.py
iza/plots.py
iza/rich.py
iza/static.py
iza/typer.py
iza/types.py
iza/utils.py
iza-0.0.16.dist-info/LICENSE
iza-0.0.16.dist-info/METADATA
iza-0.0.16.dist-info/WHEEL
iza-0.0.16.dist-info/entry_points.txt
iza-0.0.16.dist-info/top_level.txt
iza-0.0.16.dist-info/RECORD
