Metadata-Version: 2.1
Name: iza
Version: 0.0.16
Summary: chaos package of utilities; a nod to izalith
Home-page: https://github.com/dsm-72/iza
Author: dsm-72
Author-email: sumner.magruder@yale.edu
License: Apache Software License 2.0
Keywords: nbdev jupyter notebook python
Classifier: Development Status :: 4 - Beta
Classifier: Intended Audience :: Developers
Classifier: Natural Language :: English
Classifier: Programming Language :: Python :: 3.10
Classifier: License :: OSI Approved :: Apache Software License
Requires-Python: >=3.10
License-File: LICENSE
Requires-Dist: pandas
Requires-Dist: seaborn
Requires-Dist: scikit-learn
Requires-Dist: numpy (>=1.22)
Requires-Dist: nbformat
Requires-Dist: rich
Requires-Dist: typer
Requires-Dist: requests
Requires-Dist: tqdm
Requires-Dist: ipos
Provides-Extra: dev
